jupyter_openbis_authenticator/auth.py
jupyter_openbis_authenticator-0.2.3.dist-info/DESCRIPTION.rst
jupyter_openbis_authenticator-0.2.3.dist-info/METADATA
jupyter_openbis_authenticator-0.2.3.dist-info/RECORD
jupyter_openbis_authenticator-0.2.3.dist-info/WHEEL
jupyter_openbis_authenticator-0.2.3.dist-info/metadata.json
jupyter_openbis_authenticator-0.2.3.dist-info/top_level.txt
jupyter_openbis_authenticator-0.2.3.dist-info/zip-safe
