Metadata-Version: 2.0
Name: jupyter-openbis-authenticator
Version: 0.2.3
Summary: An authenticator for Jupyterhub which authenticates against openBIS.
Home-page: https://sissource.ethz.ch/sispub/jupyter-openbis-integration/
Author: SIS | ID | ETH Zuerich
Author-email: swen@ethz.ch
License: BSD
Platform: UNKNOWN
Requires-Dist: jupyterhub (>=0.8.0)
Requires-Dist: pybis (>=1.5.0)
Requires-Dist: pytest
